conversion_metrics/__init__.py
conversion_metrics/_nbdev.py
conversion_metrics/plot.py
conversion_metrics/ratio.py
conversion_metrics-2.0.0.dist-info/LICENSE
conversion_metrics-2.0.0.dist-info/METADATA
conversion_metrics-2.0.0.dist-info/WHEEL
conversion_metrics-2.0.0.dist-info/entry_points.txt
conversion_metrics-2.0.0.dist-info/top_level.txt
conversion_metrics-2.0.0.dist-info/RECORD
