Metadata-Version: 2.1
Name: conversion-metrics
Version: 2.0.0
Summary: Calculate and visualize conversion rates and related metrics.
Home-page: https://github.com/JiaxiangBU/conversion_metrics
Author: Jiaxiang Li
Author-email: alex.lijiaxiang@foxmail.com
License: Apache Software License 2.0
Keywords: conversion metrics
Platform: UNKNOWN
Classifier: Development Status :: 3 - Alpha
Classifier: Intended Audience :: Developers
Classifier: License :: OSI Approved :: Apache Software License
Classifier: Natural Language :: English
Classifier: Programming Language :: Python :: 3.6
Classifier: Programming Language :: Python :: 3.7
Classifier: Programming Language :: Python :: 3.8
Requires-Python: >=3.6
